cloudfeaster/__init__.py
cloudfeaster/jsonschemas.py
cloudfeaster/privacy.py
cloudfeaster/spider.py
cloudfeaster/util.py
cloudfeaster/jsonschemas/crawl_result.json
cloudfeaster/jsonschemas/spider_metadata.json
cloudfeaster/samples/__init__.py
cloudfeaster/samples/alpine_releases.py
cloudfeaster/samples/pypi.py
cloudfeaster/samples/pythonwheels.py
cloudfeaster/samples/run-sample.sh
cloudfeaster/samples/xe_exchange_rates.py
cloudfeaster/tests/__init__.py
cloudfeaster/tests/privacy_tests.py
cloudfeaster/tests/spider_tests.py
cloudfeaster/tests/util_tests.py
cloudfeaster/tests/data/chrome-driver-log.txt
cloudfeaster/tests/data/crawl-output.json
cloudfeaster/tests/data/empty.txt
cloudfeaster/tests/data/python-magic-pypi.pdf
cloudfeaster/tests/data/screenshot.png
cloudfeaster/tests/some_test_spiders/__init__.py
cloudfeaster/tests/some_test_spiders/abstract.py
cloudfeaster/tests/some_test_spiders/supersimpleconcrete.py
cloudfeaster-0.9.59.data/scripts/check-circleci-config.sh
cloudfeaster-0.9.59.data/scripts/check-consistent-clf-version.sh
cloudfeaster-0.9.59.data/scripts/generate-circleci-config.py
cloudfeaster-0.9.59.data/scripts/get-clf-version.sh
cloudfeaster-0.9.59.data/scripts/int-test-run-all-spiders-in-ci-pipeline.py
cloudfeaster-0.9.59.data/scripts/run-all-spiders.sh
cloudfeaster-0.9.59.data/scripts/run-spider.sh
cloudfeaster-0.9.59.data/scripts/spiders.py
cloudfeaster_extension/__init__.py
cloudfeaster_extension/tests/__init__.py
cloudfeaster-0.9.59.dist-info/LICENSE.md
cloudfeaster-0.9.59.dist-info/METADATA
cloudfeaster-0.9.59.dist-info/WHEEL
cloudfeaster-0.9.59.dist-info/top_level.txt
cloudfeaster-0.9.59.dist-info/RECORD
