Metadata-Version: 2.1
Name: cloudfeaster
Version: 0.9.59
Summary: Cloudfeaster
Home-page: https://github.com/simonsdave/cloudfeaster
Author: Dave Simons
Author-email: simonsdave@gmail.com
Maintainer: Dave Simons
Maintainer-email: simonsdave@gmail.com
License: MIT
Download-URL: https://github.com/simonsdave/cloudfeaster/tarball/v0.9.59
Keywords: selenium
Platform: UNKNOWN
Classifier: Development Status :: 5 - Production/Stable
Classifier: Intended Audience :: Developers
Classifier: Natural Language :: English
Classifier: License :: OSI Approved :: MIT License
Classifier: Operating System :: OS Independent
Classifier: Programming Language :: Python
Classifier: Programming Language :: Python :: 3.9
Classifier: Programming Language :: Python :: Implementation :: CPython
Classifier: Topic :: Software Development :: Libraries :: Python Modules
Requires-Dist: colorama (>=0.3.5)
Requires-Dist: jsonschema (>=2.3.0)
Requires-Dist: python-dateutil (==2.8.2)
Requires-Dist: selenium (==4.1.0)
